proact/__colors__.py
proact/__disp__.py
proact/__init__.py
proact/__main__.py
proact/__version__.py
proact/config.json
proact/__pycache__/__version__.cpython-39.pyc
proact-0.0.0.dist-info/LICENSE.txt
proact-0.0.0.dist-info/METADATA
proact-0.0.0.dist-info/WHEEL
proact-0.0.0.dist-info/top_level.txt
proact-0.0.0.dist-info/RECORD
