Metadata-Version: 2.1
Name: proact
Version: 0.0.0
Summary: Python-based Life Cycle Assessment (LCA)
Author: Hedi ROMDHANA
Author-email: hedi.romdhana@agroparistech.fr
License: GPLv3
Keywords: LCA
Classifier: Development Status :: 3 - Alpha
Classifier: Intended Audience :: Developers
Classifier: Programming Language :: Python :: 3.4
Classifier: Programming Language :: Python :: 3.5
Classifier: Programming Language :: Python :: 3.6
Classifier: Topic :: Software Development :: Testing
Classifier: License :: OSI Approved :: GNU General Public License v3 (GPLv3)
Requires-Python: >=3.4
License-File: LICENSE.txt
